setup.py
utils.py
py2utils.egg-info/PKG-INFO
py2utils.egg-info/SOURCES.txt
py2utils.egg-info/dependency_links.txt
py2utils.egg-info/requires.txt
py2utils.egg-info/top_level.txt